Metadata-Version: 2.1
Name: odoo11-addon-sale-stock-picking-blocking-proc-group-by-line
Version: 11.0.1.0.1
Summary: Module that allows module sale_stock_picking_blocking to work with sale_procurement_group_by_line
Home-page: https://github.com/OCA/sale-workflow
Author: Eficent, Odoo Community Association (OCA)
Author-email: support@odoo-community.org
License: AGPL-3
Platform: UNKNOWN
Classifier: Programming Language :: Python
Classifier: Framework :: Odoo
Classifier: Framework :: Odoo :: 11.0
Classifier: License :: OSI Approved :: GNU Affero General Public License v3
Requires-Python: >=2.7, !=3.0.*, !=3.1.*, !=3.2.*, !=3.3.*, !=3.4.*
Requires-Dist: odoo11-addon-sale-procurement-group-by-line
Requires-Dist: odoo11-addon-sale-stock-picking-blocking
Requires-Dist: odoo (<11.1dev,>=11.0a)
